{"cameraMode":{"drawMode":0,"name":"Shaded","section":"Shading Mode"},"sceneLighting":true,"audioPlay":false,"sceneViewState":{"showFog":true,"showMaterialUpdate":false,"showSkybox":true,"showFlares":true,"showImageEffects":true,"showParticleSystems":true},"in2DMode":false,"pivot":{"x":2.7230939865112306,"y":4.846384048461914,"z":29.88595199584961},"rotation":{"x":0.15091678500175477,"y":0.011236353777348996,"z":-0.0016941364156082273,"w":0.9885239005088806},"size":12.309615135192871,"orthographic":false}